flowchronicle/attribute_value.py
flowchronicle/bayesian_network.py
flowchronicle/cover.py
flowchronicle/dataloader.py
flowchronicle/domain_knowledge.py
flowchronicle/mdl_util.py
flowchronicle/model.py
flowchronicle/our_globals.py
flowchronicle/pattern.py
flowchronicle/preprocess.py
flowchronicle/row_pattern.py
flowchronicle/search.py
flowchronicle/temporal_sampling.py
flowchronicle/window.py
flowchronicle-0.1.0.dist-info/LICENSE
flowchronicle-0.1.0.dist-info/METADATA
flowchronicle-0.1.0.dist-info/WHEEL
flowchronicle-0.1.0.dist-info/top_level.txt
flowchronicle-0.1.0.dist-info/RECORD
