Metadata-Version: 2.1
Name: flowchronicle
Version: 0.1.0
Summary: Network flow records data miner and generator
Author: Joscha Cüppers, Pierre-François Gimenez and Adrien Schoen
License: MIT
License-File: LICENSE
Requires-Dist: numpy
Requires-Dist: scikit-learn
Requires-Dist: pandas
Requires-Dist: bidict
Requires-Dist: pgmpy
Requires-Dist: tqdm
